{
    "Firewatch Background":[
        {
            "id":    "2018_1",
            "price": "`1500` coins"
        }
    ],
    "Walker Background":[
        {
            "id":    "2018_2",
            "price": "`500` coins"
        }
    ],
    "Ether Background":[
        {
            "id":    "2018_3",
            "price": "`1000` coins"
        }
    ],
    "The Division Background":[
        {
            "id":    "2018_4",
            "price": "`500` coins"
        }
    ],
    "Limbo Background":[
        {
            "id":    "2018_5",
            "price": "`300` coins"
        }
    ],
    "No Man's Sky Background":[
        {
            "id":    "2018_6",
            "price": "`1500` coins"
        }
    ],
    "The Division 2 Capitol Shootout Background":[
        {
            "id":    "2018_7",
            "price": "`1000` coins"
        }
    ],
    "Tomb Raider Background":[
        {
            "id":    "2018_8",
            "price": "`600` coins"
        }
    ],
    "Hunter Background":[
        {
            "id":    "2018_9",
            "price": "`750` coins"
        }
    ],
    "Mountains Background":[
        {
            "id":    "2018_10",
            "price": "`2000` coins"
        }
    ],
    "Wolf Background":[
        {
            "id":    "2018_11",
            "price": "`2000` coins"
        }
    ],
    "Lake Background":[
        {
            "id":    "2018_12",
            "price": "`2000` coins"
        }
    ],
    "8-bit Background":[
        {
            "id":    "8bit",
            "price": "`400` coins"
        }
    ],
    "ArmA 3 Background":[
        {
            "id":    "arma",
            "price": "`250` coins"
        }
    ],
    "Clouds Background":[
        {
            "id":    "clouds",
            "price": "`350` coins"
        }
    ],
    "Cyberpunk Background":[
        {
            "id":    "cyberpunk",
            "price": "`500` coins"
        }
    ],
    "Limbo II Background":[
        {
            "id":    "limbo",
            "price": "`350` coins"
        }
    ],
    "Ori and the Blind Forest Background":[
        {
            "id":    "ori",
            "price": "`1000` coins"
        }
    ],
    "Outbreak Background":[
        {
            "id":    "outbreak",
            "price": "`500` coins"
        }
    ],
    "Soyuz Background":[
        {
            "id":    "soyuz",
            "price": "`400` coins"
        }
    ],
    "Titan Background":[
        {
            "id":    "titan",
            "price": "`700` coins"
        }
    ],
    "To The Moon Background":[
        {
            "id":    "tothemoon",
            "price": "`300` coins"
        }
    ],
    "Ghost of Tsushima Background":[
        {
            "id":    "tsushima",
            "price": "`700` coins"
        }
    ]
}